{"header": ["paper", "code", "MNLI", "SNLI", "link"], "content": [{"paper": "[ACL 2020]Are Natural Language Inference Models IMPPRESsive? Learning IMPlicature and\nPRESupposition", "code": "\u65e0", "MNLI": "No", "SNLI": "Yes", "link": "https://www.aclweb.org/anthology/2020.acl-main.768.pdf"}, {"paper": "[ACL 2020]NILE : Natural Language Inference with Faithful Natural Language Explanations", "code": "https://github.com/SawanKumar28/nile", "MNLI": "Yes", "SNLI": "Yes", "link": "https://www.aclweb.org/anthology/2020.acl-main.771.pdf"}, {"paper": "[ACL 2020]Uncertain Natural Language Inference", "code": "https://github.com/ctongfei/unli", "MNLI": "No", "SNLI": "Yes", "link": "https://www.aclweb.org/anthology/2020.acl-main.774.pdf"}, {"paper": "[ACL 2020]Joint Training with Semantic Role Labeling for Better Generalization in Natural Language Inference", "code": "https://github.com/huggingface/hmtl", "MNLI": "No", "SNLI": "Yes", "link": "https://www.aclweb.org/anthology/2020.repl4nlp-1.11.pdf"}, {"paper": "[ACL 2020]Towards Robustifying NLI Models Against Lexical Dataset Biases", "code": "https://github.com/owenzx/LexicalDebias-ACL2020", "MNLI": "Yes", "SNLI": "No", "link": "https://arxiv.org/pdf/2005.04732.pdf"}, {"paper": "[ACL 2020]Neural Graph Matching Networks for Chinese Short Text Matching", "code": "\u65e0", "MNLI": "No", "SNLI": "No", "link": "https://www.aclweb.org/anthology/2020.acl-main.547.pdf"}, {"paper": "[ACL 2020]Rationalizing Text Matching: Learning Sparse Alignments via Optimal\nTransport", "code": "https://github.com/asappresearch/rationale-alignment", "MNLI": "No", "SNLI": "Yes", "link": "https://www.aclweb.org/anthology/2020.acl-main.496.pdf"}, {"paper": "[ACL 2019]Don\u2019t Take the Premise for Granted: Mitigating Artifacts in Natural Language Inference", "code": "\u65e0", "MNLI": "Yes", "SNLI": "Yes", "link": "https://www.aclweb.org/anthology/P19-1084.pdf"}, {"paper": "[ACL 2019]Simple and Effective Text Matching with Richer Alignment Features (RE2)", "code": "https://github.com/alibaba-edu/simple-effective-text-matching-pytorch", "MNLI": "No", "SNLI": "Yes", "link": "https://arxiv.org/pdf/1908.00300.pdf"}, {"paper": "[ACL 2019]SherLIiC: A Typed Event-Focused Lexical Inference Benchmark for Evaluating Natural Language Inference", "code": "https://github.com/mnschmit/SherLIiC", "MNLI": "No", "SNLI": "Yes", "link": "https://www.aclweb.org/anthology/P19-1086.pdf"}, {"paper": "[ACL 2019]Ranking Generated Summaries by Correctness: An Interesting but\nChallenging Application for Natural Language Inference", "code": "\u65e0", "MNLI": "No", "SNLI": "Yes", "link": "https://www.aclweb.org/anthology/P19-1213.pdf"}, {"paper": "[ACL 2019]Right for the Wrong Reasons: Diagnosing Syntactic Heuristics in Natural Language Inference", "code": "\u65e0", "MNLI": "Yes", "SNLI": "Yes", "link": "https://www.aclweb.org/anthology/P19-1334.pdf"}, {"paper": "[ACL 2019]Dialogue Natural Language Inference", "code": "\u65e0", "MNLI": "No", "SNLI": "Yes", "link": "https://www.aclweb.org/anthology/P19-1363.pdf"}, {"paper": "[ACL 2018]Discourse Marker Augmented Network with Reinforcement Learning for\nNatural Language Inference", "code": "\u65e0", "MNLI": "No", "SNLI": "Yes", "link": "https://www.aclweb.org/anthology/P18-1091.pdf"}, {"paper": "[ACL 2018]Neural Natural Language Inference Models Enhanced with External Knowledge", "code": "https://github.com/lukecq1231/nli (theESIM core code has also been adapted to sum-marization (Chen et al., 2016a) and question-answering tasks\n(Zhang et al., 2017a))", "MNLI": "No", "SNLI": "Yes", "link": "https://www.aclweb.org/anthology/P18-1224.pdf"}, {"paper": "[ACL 2017]Enhanced LSTM for Natural Language Inference", "code": "https://github.com/lukecq1231/nli#enhanced-lstm-for-natural-language-inference", "MNLI": "No", "SNLI": "Yes", "link": "https://www.aclweb.org/anthology/P17-1152.pdf"}, {"paper": "[ACL 2016]Natural Language Inference by Tree-Based Convolution and Heuristic Matching", "code": "\u65e0", "MNLI": "No", "SNLI": "Yes", "link": "https://arxiv.org/pdf/1512.08422.pdf"}, {"paper": "[ACL 2015] MultiGranCNN: An Architecture for General Matching of Text Chunks on Multiple Levels of Granularity", "code": "\u65e0", "MNLI": "No", "SNLI": "No", "link": "https://www.aclweb.org/anthology/P15-1007.pdf"}, {"paper": "[AAAI 2020]Enhancing Natural Language Inference Using New and Expanded Training Data Sets and New Learning Models", "code": "\u65e0", "MNLI": "Yes", "SNLI": "Yes", "link": "https://ojs.aaai.org/index.php/AAAI/article/view/6371"}, {"paper": "[AAAI 2020]Translation-Based Matching Adversarial Network for Cross-Lingual Natural Language Inference", "code": "\u65e0", "MNLI": "No", "SNLI": "No", "link": "https://ojs.aaai.org/index.php/AAAI/article/view/6387"}, {"paper": "[AAAI 2020]Probing Natural Language Inference Models through Semantic Fragments", "code": "\u65e0", "MNLI": "Yes", "SNLI": "Yes", "link": "https://ojs.aaai.org/index.php/AAAI/article/view/6397"}, {"paper": "[AAAI 2020]Generating Persona Consistent Dialogues by Exploiting Natural Language Inference", "code": "\u65e0", "MNLI": "No", "SNLI": "Yes", "link": "https://ojs.aaai.org/index.php/AAAI/article/view/6417"}, {"paper": "[AAAI 2020]Semantics-Aware BERT for Language Understanding", "code": "https://github.com/cooelf/SemBERT", "MNLI": "Yes", "SNLI": "Yes", "link": "https://ojs.aaai.org/index.php/AAAI/article/view/6510"}, {"paper": "[AAAI 2019]Combining Axiom Injection and Knowledge Base Completion for Efficient Natural\nLanguage Inference", "code": "\u65e0", "MNLI": "No", "SNLI": "Yes", "link": "https://ojs.aaai.org/index.php/AAAI/article/view/4730"}, {"paper": "[AAAI 2019]Gaussian Transformer: a Lightweight Approach for Natural Language Inference", "code": "\u65e0", "MNLI": "Yes", "SNLI": "Yes", "link": "https://ojs.aaai.org/index.php/AAAI/article/view/4614"}, {"paper": "[AAAI 2019]Improving Natural Language Inference Using External Knowledge in the Science\nQuestions Domain", "code": "\u65e0", "MNLI": "No", "SNLI": "Yes", "link": "https://ojs.aaai.org/index.php/AAAI/article/view/4705"}, {"paper": "[EMNLP 2020]Discriminative Nearest Neighbor Few-Shot Intent Detection by Transferring Natural Language Inference", "code": "https://github.com/clinc/oos-eval", "MNLI": "Yes", "SNLI": "Yes", "link": "https://www.aclweb.org/anthology/2020.emnlp-main.411.pdf"}, {"paper": "[EMNLP 2020]Unsupervised Natural Language Inference via Decoupled Multimodal\nContrastive Learning", "code": "\u65e0", "MNLI": "No", "SNLI": "Yes", "link": "https://www.aclweb.org/anthology/2020.emnlp-main.444.pdf"}, {"paper": "[EMNLP 2020]Discriminatively-Tuned Generative Classifiers for Robust Natural Language Inference", "code": "https://github.com/tyliupku/gen-nli", "MNLI": "Yes", "SNLI": "Yes", "link": "https://www.aclweb.org/anthology/2020.emnlp-main.657.pdf"}, {"paper": "[EMNLP 2020]Data and Representation for Turkish Natural Language Inference", "code": "https://github.com/boun-tabi/NLI-TR", "MNLI": "No", "SNLI": "Yes", "link": "https://www.aclweb.org/anthology/2020.emnlp-main.662.pdf"}, {"paper": "[EMNLP 2020]Avoiding the Hypothesis-Only Bias in Natural Language Inference via Ensemble Adversarial Training", "code": "https://github.com/joestacey/", "MNLI": "Yes", "SNLI": "Yes", "link": "https://www.aclweb.org/anthology/2020.emnlp-main.665.pdf"}, {"paper": "[EMNLP 2020]An Analysis of Natural Language Inference Benchmarks through the Lens of Negation", "code": "\u65e0", "MNLI": "Yes", "SNLI": "Yes", "link": "https://www.aclweb.org/anthology/2020.emnlp-main.732.pdf"}, {"paper": "[EMNLP 2020]What Can We Learn from Collective Human Opinions on Natural Language Inference Data?", "code": "https://github.com/easonnie/ChaosNLI", "MNLI": "Yes", "SNLI": "Yes", "link": "https://www.aclweb.org/anthology/2020.emnlp-main.734.pdf"}, {"paper": "[EMNLP 2020]Neural Natural Language Inference Models Partially Embed Theories of\nLexical Entailment and Negation", "code": "\u65e0", "MNLI": "Yes", "SNLI": "Yes", "link": "https://www.aclweb.org/anthology/2020.blackboxnlp-1.16.pdf"}, {"paper": "[EMNLP 2020]Mining Knowledge for Natural Language Inference from Wikipedia Categories", "code": "https://github.com/ZeweiChu/WikiNLI", "MNLI": "Yes", "SNLI": "No", "link": "https://www.aclweb.org/anthology/2020.findings-emnlp.313.pdf"}, {"paper": "[EMNLP 2020]OCNLI: Original Chinese Natural Language Inference", "code": "\u65e0", "MNLI": "Yes", "SNLI": "Yes", "link": "https://www.aclweb.org/anthology/2020.findings-emnlp.314.pdf"}, {"paper": "[EMNLP 2020]Temporal Reasoning in Natural Language Inference", "code": "\u65e0", "MNLI": "Yes", "SNLI": "No", "link": "https://www.aclweb.org/anthology/2020.findings-emnlp.363.pdf"}, {"paper": "[EMNLP 2020]Enhancing Generalization in Natural Language Inference by Syntax", "code": "\u65e0", "MNLI": "Yes", "SNLI": "No", "link": "https://www.aclweb.org/anthology/2020.findings-emnlp.447.pdf"}, {"paper": "[EMNLP 2020]On the Sentence Embeddings from Pre-trained Language Models", "code": "https://github.com/bohanli/BERT-flow", "MNLI": "Yes", "SNLI": "Yes", "link": "https://arxiv.org/pdf/2011.05864.pdf"}, {"paper": "[EMNLP 2020]Wasserstein Distance Regularized Sequence Representation for Text\nMatching in Asymmetrical Domains", "code": "https://github.com/RUC-WSM/WD-Match", "MNLI": "No", "SNLI": "Yes", "link": "https://www.aclweb.org/anthology/2020.emnlp-main.239.pdf"}, {"paper": "[EMNLP 2020]Enhanced Sentence Alignment Network for Efficient Short Text Matching", "code": "\u65e0", "MNLI": "No", "SNLI": "Yes", "link": "https://www.aclweb.org/anthology/2020.wnut-1.6.pdf"}, {"paper": "[EMNLP 2019]Asynchronous Deep Interaction Network for Natural Language Inference", "code": "\u65e0", "MNLI": "No", "SNLI": "Yes", "link": "https://www.aclweb.org/anthology/D19-1271.pdf"}, {"paper": "[EMNLP 2019]Posing Fair Generalization Tasks for Natural Language Inference", "code": "\u65e0", "MNLI": "No", "SNLI": "Yes", "link": "https://www.aclweb.org/anthology/D19-1456.pdf"}, {"paper": "[EMNLP 2019]Evaluating BERT for natural language inference: A case study on the CommitmentBank", "code": "\u65e0", "MNLI": "Yes", "SNLI": "Yes", "link": "https://www.aclweb.org/anthology/D19-1630.pdf"}, {"paper": "[EMNLP 2019]Sentence-BERT: Sentence Embeddings using Siamese BERT-Networks", "code": "https://github.com/UKPLab/sentence-transformers", "MNLI": "No", "SNLI": "Yes", "link": "https://arxiv.org/pdf/1908.10084.pdf"}, {"paper": "[EMNLP 2019]Incorporating Contextual and Syntactic Structures Improves Semantic\nSimilarity Modeling", "code": "https://github.com/likicode/spwim", "MNLI": "Yes", "SNLI": "Yes", "link": "https://www.aclweb.org/anthology/D19-1114.pdf"}, {"paper": "[EMNLP 2018]Collecting Diverse Natural Language Inference Problems for Sentence\nRepresentation Evaluation", "code": "\u65e0", "MNLI": "No", "SNLI": "Yes", "link": "https://www.aclweb.org/anthology/D18-1007.pdf"}, {"paper": "[EMNLP 2018]Convolutional Interaction Network for Natural Language Inference", "code": "\u65e0", "MNLI": "No", "SNLI": "Yes", "link": "https://www.aclweb.org/anthology/D18-1186.pdf"}, {"paper": "[EMNLP 2018]Lessons from Natural Language Inference in the Clinical Domain", "code": "\u65e0", "MNLI": "No", "SNLI": "Yes", "link": "https://www.aclweb.org/anthology/D18-1187.pdf"}, {"paper": "[EMNLP 2018]InferLite: Simple Universal Sentence Representations from Natural Language Inference Data", "code": "https://github.com/Smerity/keras_snli", "MNLI": "No", "SNLI": "Yes", "link": "https://www.aclweb.org/anthology/D18-1524.pdf"}, {"paper": "[EMNLP 2018]When data permutations are pathological: the case of neural natural language inference", "code": "https://github.com/natschluter/nli-data-permutations", "MNLI": "No", "SNLI": "Yes", "link": "https://www.aclweb.org/anthology/D18-1534.pdf"}, {"paper": "[EMNLP 2018]Visual Interrogation of Attention-Based Models for Natural Language\nInference and Machine Comprehension", "code": "\u65e0", "MNLI": "No", "SNLI": "No", "link": "https://www.aclweb.org/anthology/D18-2007.pdf"}, {"paper": "[EMNLP 2018]Collecting Diverse Natural Language Inference Problems for Sentence\nRepresentation Evaluation", "code": "\u65e0", "MNLI": "No", "SNLI": "Yes", "link": "https://www.aclweb.org/anthology/W18-5441.pdf"}, {"paper": "[EMNLP 2017]Supervised Learning of Universal Sentence Representations from Natural\nLanguage Inference Data", "code": "https://github.com/facebookresearch/InferSent", "MNLI": "No", "SNLI": "No", "link": "https://www.aclweb.org/anthology/D17-1070.pdf"}, {"paper": "[EMNLP 2016]A Decomposable Attention Model for Natural Language Inference", "code": "https://github.com/HsiaoYetGun/Decomposable-Attention", "MNLI": "No", "SNLI": "No", "link": "https://www.aclweb.org/anthology/D16-1244.pdf"}, {"paper": "[EMNLP 2015]A large annotated corpus for learning natural language inference", "code": "\u65e0", "MNLI": "No", "SNLI": "No", "link": "https://www.aclweb.org/anthology/D15-1075.pdf"}, {"paper": "[EMNLP 2008]A Phrase-Based Alignment Model for Natural Language Inference", "code": "\u65e0", "MNLI": "No", "SNLI": "No", "link": "https://www.aclweb.org/anthology/D08-1084.pdf"}, {"paper": "[NAACL 2019]Generating Token-Level Explanations for Natural Language Inference", "code": "\u65e0", "MNLI": "No", "SNLI": "Yes", "link": "https://www.aclweb.org/anthology/N19-1101.pdf"}, {"paper": "[NAACL 2018]DR-BiLSTM: Dependent Reading Bidirectional LSTM for Natural Language\nInference", "code": "\u65e0", "MNLI": "No", "SNLI": "No", "link": "https://www.aclweb.org/anthology/N18-1132.pdf"}, {"paper": "[NAACL 2016]Learning Natural Language Inference with LSTM", "code": "https://github.com/donghyeonk/match-lstm", "MNLI": "No", "SNLI": "No", "link": "https://www.aclweb.org/anthology/N16-1170.pdf"}, {"paper": "[COLING 2020]Combining Event Semantics and Degree Semantics for Natural Language Inference", "code": "https://github.com/izumi-h/ccgcomp", "MNLI": "No", "SNLI": "No", "link": "https://www.aclweb.org/anthology/2020.coling-main.156.pdf"}, {"paper": "[COLING 2020]Hy-NLI: a Hybrid system for Natural Language Inference", "code": "https://github.com/kkalouli/GKR4NLI3Available under github.com/kkalouli/GKR_semantic_parser", "MNLI": "Yes", "SNLI": "Yes", "link": "https://www.aclweb.org/anthology/2020.coling-main.459.pdf"}, {"paper": "[COLING 2020]Knowledge-Enhanced Natural Language Inference Based on Knowledge Graphs", "code": "\u65e0", "MNLI": "No", "SNLI": "Yes", "link": "https://www.aclweb.org/anthology/2020.coling-main.571.pdf"}, {"paper": "[COLING 2020]XplaiNLI: Explainable Natural Language Inference through Visual Analytics", "code": "https://github.com/kkalouli/XplaiNLI", "MNLI": "Yes", "SNLI": "Yes", "link": "https://www.aclweb.org/anthology/2020.coling-demos.9.pdf"}, {"paper": "[COLING 2020]Reading Comprehension as Natural Language Inference:A Semantic Analysis", "code": "\u65e0", "MNLI": "No", "SNLI": "Yes", "link": "https://www.aclweb.org/anthology/2020.starsem-1.2.pdf"}, {"paper": "[COLING 2020]Learning as Abduction: Trainable Natural Logic Theorem Prover for Natural Language Inference", "code": "https://github.com/kovvalsky/LangPro", "MNLI": "No", "SNLI": "No", "link": "https://www.aclweb.org/anthology/2020.starsem-1.3.pdf"}, {"paper": "[COLING 2020]Natural Language Inference with Mixed Effects", "code": "\u65e0", "MNLI": "No", "SNLI": "No", "link": "https://www.aclweb.org/anthology/2020.starsem-1.9.pdf"}, {"paper": "[COLING 2020]FASTMATCH: Accelerating the Inference of BERT-based Text Matching", "code": "\u65e0", "MNLI": "Yes", "SNLI": "No", "link": "https://www.aclweb.org/anthology/2020.coling-main.568.pdf"}, {"paper": "[COLING 2020]Specializing Unsupervised Pretraining Models for Word-Level Semantic Similarity", "code": "\u65e0", "MNLI": "Yes", "SNLI": "No", "link": "https://www.aclweb.org/anthology/2020.coling-main.118.pdf"}, {"paper": "[COLING 2018]Adopting the Word-Pair-Dependency-Triplets with Individual Comparison\nfor Natural Language Inference", "code": "\u65e0", "MNLI": "No", "SNLI": "Yes", "link": "https://www.aclweb.org/anthology/C18-1035.pdf"}, {"paper": "[COLING 2018]Stress Test Evaluation for Natural Language Inference", "code": "\u65e0", "MNLI": "No", "SNLI": "Yes", "link": "https://www.aclweb.org/anthology/C18-1198.pdf"}, {"paper": "[COLING 2018]Neural Network Models for Paraphrase Identification, Semantic Textual Similarity, Natural Language\nInference, and Question Answering", "code": "https://github.com/lanwuwei/SPM_toolkit", "MNLI": "No", "SNLI": "Yes", "link": "https://www.aclweb.org/anthology/C18-1328.pdf"}, {"paper": "[COLING 2008]Modeling Semantic Containment and Exclusion in Natural Language\nInference", "code": "\u65e0", "MNLI": "No", "SNLI": "No", "link": "https://www.aclweb.org/anthology/C08-1066.pdf"}, {"paper": "[IJCAI 2018]Attention-Fused Deep Matching Network for Natural Language Inference", "code": "\u65e0", "MNLI": "No", "SNLI": "No", "link": "https://www.ijcai.org/proceedings/2018/0561.pdf"}, {"paper": "[IJCAI 2018]Multiway Attention Networks for Modeling Sentence Pairs", "code": "\u65e0", "MNLI": "Yes", "SNLI": "Yes", "link": "https://www.ijcai.org/Proceedings/2018/0613.pdf"}, {"paper": "[IJCAI 2018]Hermitian Co-Attention Networks for Text Matching in Asymmetrical Domains", "code": "\u65e0", "MNLI": "No", "SNLI": "No", "link": "https://www.ijcai.org/Proceedings/2018/0615.pdf"}, {"paper": "[IJCAI 2017]Bilateral Multi-Perspective Matching for Natural Language Sentences", "code": "https://github.com/zhiguowang/BiMPM", "MNLI": "No", "SNLI": "Yes", "link": "https://arxiv.org/pdf/1702.03814.pdf"}, {"paper": "[IJCAI 2016]Match-SRNN: Modeling the Recursive Matching Structure with Spatial RNN", "code": "\u65e0", "MNLI": "No", "SNLI": "No", "link": "https://arxiv.org/pdf/1604.04378.pdf"}, {"paper": "[ICLR2018]Learning General Purpose Distributed Sentence Representations via Large Scale Multi-task Learning", "code": "https://github.com/Maluuba/gensen", "MNLI": "Yes", "SNLI": "Yes", "link": "https://arxiv.org/pdf/1804.00079.pdf"}, {"paper": "[ICLR 2018]Natural Language Inference Over Interaction Space", "code": "https://github.com/YichenGong/Densely-Interactive-Inference-Network", "MNLI": "No", "SNLI": "Yes", "link": "https://arxiv.org/pdf/1802.03198.pdf"}, {"paper": "[ICLR 2016]Reasoning about Entailment with Neural Attention", "code": "\u65e0", "MNLI": "No", "SNLI": "Yes", "link": "https://arxiv.org/pdf/1509.06664.pdf"}, {"paper": "[NIPS 2014]Convolutional Neural Network Architectures for Matching Natural Language Sentences", "code": "\u65e0", "MNLI": "No", "SNLI": "No", "link": "https://arxiv.org/pdf/1503.03244.pdf"}]}